<T3DataStructure>
	<meta>
		<langDisable>1</langDisable>
	</meta>
	<sheets>
		<sDEF>
			<ROOT>
				<TCEforms>
					<sheetTitle>LLL:EXT:li_gest_membre_labo/locallang_db.xml:tt_content.pi_flexform.sheet_general</sheetTitle>
				</TCEforms>
				<type>array</type>
				<el>
					<labo>
						<TCEforms>
							<exclude>1</exclude>
							<label>LLL:EXT:li_gest_membre_labo/locallang_db.xml:tt_content.pi_flexform.labo</label>
							<config>
								<type>input</type>
								<size>30</size>
							</config>
						</TCEforms>
					</labo>
					<poste>
						<TCEforms>
							<label>LLL:EXT:li_gest_membre_labo/locallang_db.xml:tt_content.pi_flexform.poste</label>
							<config>
								<type>check</type>
							</config>
						</TCEforms>
					</poste>
				</el>
		    </ROOT>
		</sDEF>
		<display>
		    <ROOT>
				<TCEforms>
					<sheetTitle>LLL:EXT:li_gest_membre_labo/locallang_db.xml:tt_content.pi_flexform.sheet_display</sheetTitle>
				</TCEforms>
				<type>array</type>
				<el>
					<professeur>
						<TCEforms>
							<label>LLL:EXT:li_gest_membre_labo/locallang_db.xml:tt_content.pi_flexform.professeur</label>
							<config>
								<type>check</type>
								<default>1</default>
							</config>
						</TCEforms>
					</professeur>
					<maitre>
						<TCEforms>
							<label>LLL:EXT:li_gest_membre_labo/locallang_db.xml:tt_content.pi_flexform.maitre</label>
							<config>
								<type>check</type>
								<default>1</default>
							</config>
						</TCEforms>
					</maitre>
					<docteur>
						<TCEforms>
							<label>LLL:EXT:li_gest_membre_labo/locallang_db.xml:tt_content.pi_flexform.docteur</label>
							<config>
								<type>check</type>
								<default>1</default>
							</config>
						</TCEforms>
					</docteur>
					<doctorant>
						<TCEforms>
							<label>LLL:EXT:li_gest_membre_labo/locallang_db.xml:tt_content.pi_flexform.doctorant</label>
							<config>
								<type>check</type>
								<default>1</default>
							</config>
						</TCEforms>
					</doctorant>
					<autre>
						<TCEforms>
							<label>LLL:EXT:li_gest_membre_labo/locallang_db.xml:tt_content.pi_flexform.autre</label>
							<config>
								<type>check</type>
								<default>1</default>
							</config>
						</TCEforms>
					</autre>
					<pid>
						<TCEforms>
							<label>LLL:EXT:li_gest_membre_labo/locallang_db.xml:tt_content.pi_flexform.pid</label>
							<config>
								<type>group</type>
								<internal_type>db</internal_type>
								<allowed>pages</allowed>
								<size>5</size>
								<maxitems>10</maxitems>
								<minitems>0</minitems>
								<show_thumbs>1</show_thumbs>
							</config>
						</TCEforms>
					</pid>
				</el>
		    </ROOT>
		</display>
		<request>
		    <ROOT>
				<TCEforms>
					<sheetTitle>LLL:EXT:li_gest_membre_labo/locallang_db.xml:tt_content.pi_flexform.sheet_request</sheetTitle>
				</TCEforms>
				<type>array</type>
				<el>
					<requete>
						<TCEforms>
							<label>LLL:EXT:li_gest_membre_labo/locallang_db.xml:tt_content.pi_flexform.requete</label>
							<config>
								<type>check</type>
							</config>
						</TCEforms>
					</requete>
					<select>
						<TCEforms>
							<exclude>1</exclude>
							<label>LLL:EXT:li_gest_membre_labo/locallang_db.xml:tt_content.pi_flexform.select</label>
							<config>
								<type>input</type>
								<size>30</size>
							</config>
						</TCEforms>
					</select>
					<from_table>
						<TCEforms>
							<exclude>1</exclude>
							<label>LLL:EXT:li_gest_membre_labo/locallang_db.xml:tt_content.pi_flexform.from_table</label>
							<config>
								<type>input</type>
								<size>30</size>
							</config>
						</TCEforms>
					</from_table>
					<where_clause>
						<TCEforms>
							<exclude>1</exclude>
							<label>LLL:EXT:li_gest_membre_labo/locallang_db.xml:tt_content.pi_flexform.where_clause</label>
							<config>
								<type>input</type>
								<size>30</size>
							</config>
						</TCEforms>
					</where_clause>
					<groupBy>
						<TCEforms>
							<exclude>1</exclude>
							<label>LLL:EXT:li_gest_membre_labo/locallang_db.xml:tt_content.pi_flexform.groupBy</label>
							<config>
								<type>input</type>
								<size>30</size>
							</config>
						</TCEforms>
					</groupBy>
					<orderBy>
						<TCEforms>
							<exclude>1</exclude>
							<label>LLL:EXT:li_gest_membre_labo/locallang_db.xml:tt_content.pi_flexform.orderBy</label>
							<config>
								<type>input</type>
								<size>30</size>
							</config>
						</TCEforms>
					</orderBy>
					<limit>
						<TCEforms>
							<exclude>1</exclude>
							<label>LLL:EXT:li_gest_membre_labo/locallang_db.xml:tt_content.pi_flexform.limit</label>
							<config>
								<type>input</type>
								<size>30</size>
							</config>
						</TCEforms>
					</limit>
					<tryMemcached>
						<TCEforms>
							<exclude>1</exclude>
							<label>LLL:EXT:li_gest_membre_labo/locallang_db.xml:tt_content.pi_flexform.tryMemcached</label>
							<config>
								<type>input</type>
								<size>30</size>
							</config>
						</TCEforms>
					</tryMemcached>
				</el>
			</ROOT>
		</request>
	</sheets>
</T3DataStructure>